legacy/__init__.py
legacy/configuration.py
legacy/graph.py
legacy/multi_agent.py
legacy/prompts.py
legacy/state.py
legacy/utils.py
open_deep_research/configuration.py
open_deep_research/deep_researcher.py
open_deep_research/prompts.py
open_deep_research/state.py
open_deep_research/utils.py
open_deep_research-0.0.16.dist-info/licenses/LICENSE
tests/evaluators.py
tests/pairwise_evaluation.py
tests/prompts.py
tests/run_evaluate.py
tests/supervisor_parallel_evaluation.py
open_deep_research-0.0.16.dist-info/METADATA
open_deep_research-0.0.16.dist-info/WHEEL
open_deep_research-0.0.16.dist-info/top_level.txt
open_deep_research-0.0.16.dist-info/RECORD
