Metadata-Version: 2.4
Name: open_deep_research
Version: 0.0.16
Summary: Planning, research, and report generation.
Author: Lance Martin
License: MIT
Requires-Python: >=3.10
License-File: LICENSE
Requires-Dist: langgraph>=0.2.55
Requires-Dist: langchain-community>=0.3.9
Requires-Dist: langchain-openai>=0.3.7
Requires-Dist: langchain-anthropic>=0.3.15
Requires-Dist: langchain-mcp-adapters>=0.1.6
Requires-Dist: langchain-deepseek>=0.1.2
Requires-Dist: langchain-tavily
Requires-Dist: langchain-groq>=0.2.4
Requires-Dist: openai>=1.61.0
Requires-Dist: tavily-python>=0.5.0
Requires-Dist: arxiv>=2.1.3
Requires-Dist: pymupdf>=1.25.3
Requires-Dist: xmltodict>=0.14.2
Requires-Dist: linkup-sdk>=0.2.3
Requires-Dist: duckduckgo-search>=3.0.0
Requires-Dist: exa-py>=1.8.8
Requires-Dist: requests>=2.32.3
Requires-Dist: beautifulsoup4==4.13.3
Requires-Dist: python-dotenv>=1.0.1
Requires-Dist: pytest
Requires-Dist: httpx>=0.24.0
Requires-Dist: markdownify>=0.11.6
Requires-Dist: azure-identity>=1.21.0
Requires-Dist: azure-search>=1.0.0b2
Requires-Dist: azure-search-documents>=11.5.2
Requires-Dist: rich>=13.0.0
Requires-Dist: langgraph-cli[inmem]>=0.3.1
Requires-Dist: langsmith>=0.3.37
Requires-Dist: langchain-google-vertexai>=2.0.25
Requires-Dist: langchain-google-genai>=2.1.5
Requires-Dist: ipykernel>=6.29.5
Requires-Dist: supabase>=2.15.3
Requires-Dist: mcp>=1.9.4
Requires-Dist: build>=1.2.2.post1
Requires-Dist: setuptools>=80.9.0
Requires-Dist: wheel>=0.45.1
Provides-Extra: dev
Requires-Dist: mypy>=1.11.1; extra == "dev"
Requires-Dist: ruff>=0.6.1; extra == "dev"
Dynamic: license-file
